{"FL_DATE":"2000-01-23","OP_CARRIER_FL_NUM":435,"ORIGIN_CITY_NAME":"Nashville, TN","DEST":"DEN","DEST_CITY_NAME":"Denver, CO","CRS_DEP_TIME":1510,"DEP_TIME":1507,"WHEELS_ON":1647,"TAXI_IN":5,"CRS_ARR_TIME":1648,"ARR_TIME":1652,"CANCELLED":0,"DISTANCE":1013}
{"FL_DATE":"2000-01-23","OP_CARRIER_FL_NUM":1601,"ORIGIN_CITY_NAME":"Nashville, TN","DEST":"DEN","DEST_CITY_NAME":"Denver, CO","CRS_DEP_TIME":735,"DEP_TIME":731,"WHEELS_ON":913,"TAXI_IN":8,"CRS_ARR_TIME":918,"ARR_TIME":921,"CANCELLED":0,"DISTANCE":1013}
{"FL_DATE":"2000-01-23","OP_CARRIER_FL_NUM":1101,"ORIGIN_CITY_NAME":"Nashville, TN","DEST":"ORD","DEST_CITY_NAME":"Chicago, IL","CRS_DEP_TIME":1710,"DEP_TIME":1721,"WHEELS_ON":1856,"TAXI_IN":4,"CRS_ARR_TIME":1841,"ARR_TIME":1900,"CANCELLED":0,"DISTANCE":409}
{"FL_DATE":"2000-01-23","OP_CARRIER_FL_NUM":1862,"ORIGIN_CITY_NAME":"Nashville, TN","DEST":"ORD","DEST_CITY_NAME":"Chicago, IL","CRS_DEP_TIME":942,"DEP_TIME":937,"WHEELS_ON":1102,"TAXI_IN":5,"CRS_ARR_TIME":1115,"ARR_TIME":1107,"CANCELLED":0,"DISTANCE":409}
{"FL_DATE":"2000-01-24","OP_CARRIER_FL_NUM":435,"ORIGIN_CITY_NAME":"Nashville, TN","DEST":"DEN","DEST_CITY_NAME":"Denver, CO","CRS_DEP_TIME":1510,"DEP_TIME":1512,"WHEELS_ON":1651,"TAXI_IN":4,"CRS_ARR_TIME":1648,"ARR_TIME":1655,"CANCELLED":0,"DISTANCE":1013}
{"FL_DATE":"2000-01-24","OP_CARRIER_FL_NUM":1601,"ORIGIN_CITY_NAME":"Nashville, TN","DEST":"DEN","DEST_CITY_NAME":"Denver, CO","CRS_DEP_TIME":735,"DEP_TIME":731,"WHEELS_ON":903,"TAXI_IN":17,"CRS_ARR_TIME":918,"ARR_TIME":920,"CANCELLED":0,"DISTANCE":1013}
{"FL_DATE":"2000-01-24","OP_CARRIER_FL_NUM":589,"ORIGIN_CITY_NAME":"Nashville, TN","DEST":"ORD","DEST_CITY_NAME":"Chicago, IL","CRS_DEP_TIME":714,"DEP_TIME":710,"WHEELS_ON":842,"TAXI_IN":5,"CRS_ARR_TIME":845,"ARR_TIME":847,"CANCELLED":0,"DISTANCE":409}
{"FL_DATE":"2000-01-24","OP_CARRIER_FL_NUM":1101,"ORIGIN_CITY_NAME":"Nashville, TN","DEST":"ORD","DEST_CITY_NAME":"Chicago, IL","CRS_DEP_TIME":1710,"DEP_TIME":1705,"WHEELS_ON":1825,"TAXI_IN":5,"CRS_ARR_TIME":1841,"ARR_TIME":1830,"CANCELLED":0,"DISTANCE":409}
{"FL_DATE":"2000-01-24","OP_CARRIER_FL_NUM":1862,"ORIGIN_CITY_NAME":"Nashville, TN","DEST":"ORD","DEST_CITY_NAME":"Chicago, IL","CRS_DEP_TIME":942,"DEP_TIME":938,"WHEELS_ON":1105,"TAXI_IN":6,"CRS_ARR_TIME":1115,"ARR_TIME":1111,"CANCELLED":0,"DISTANCE":409}
{"FL_DATE":"2000-01-25","OP_CARRIER_FL_NUM":435,"ORIGIN_CITY_NAME":"Nashville, TN","DEST":"DEN","DEST_CITY_NAME":"Denver, CO","CRS_DEP_TIME":1510,"DEP_TIME":1505,"WHEELS_ON":1655,"TAXI_IN":8,"CRS_ARR_TIME":1648,"ARR_TIME":1703,"CANCELLED":0,"DISTANCE":1013}
{"FL_DATE":"2000-01-25","OP_CARRIER_FL_NUM":1601,"ORIGIN_CITY_NAME":"Nashville, TN","DEST":"DEN","DEST_CITY_NAME":"Denver, CO","CRS_DEP_TIME":735,"DEP_TIME":805,"WHEELS_ON":942,"TAXI_IN":5,"CRS_ARR_TIME":918,"ARR_TIME":947,"CANCELLED":0,"DISTANCE":1013}
{"FL_DATE":"2000-01-25","OP_CARRIER_FL_NUM":589,"ORIGIN_CITY_NAME":"Nashville, TN","DEST":"ORD","DEST_CITY_NAME":"Chicago, IL","CRS_DEP_TIME":714,"DEP_TIME":712,"WHEELS_ON":825,"TAXI_IN":6,"CRS_ARR_TIME":845,"ARR_TIME":831,"CANCELLED":0,"DISTANCE":409}
{"FL_DATE":"2000-01-25","OP_CARRIER_FL_NUM":1101,"ORIGIN_CITY_NAME":"Nashville, TN","DEST":"ORD","DEST_CITY_NAME":"Chicago, IL","CRS_DEP_TIME":1710,"DEP_TIME":1707,"WHEELS_ON":1822,"TAXI_IN":5,"CRS_ARR_TIME":1841,"ARR_TIME":1827,"CANCELLED":0,"DISTANCE":409}
{"FL_DATE":"2000-01-25","OP_CARRIER_FL_NUM":1862,"ORIGIN_CITY_NAME":"Nashville, TN","DEST":"ORD","DEST_CITY_NAME":"Chicago, IL","CRS_DEP_TIME":942,"DEP_TIME":1048,"WHEELS_ON":1205,"TAXI_IN":5,"CRS_ARR_TIME":1115,"ARR_TIME":1210,"CANCELLED":0,"DISTANCE":409}
{"FL_DATE":"2000-01-26","OP_CARRIER_FL_NUM":435,"ORIGIN_CITY_NAME":"Nashville, TN","DEST":"DEN","DEST_CITY_NAME":"Denver, CO","CRS_DEP_TIME":1510,"DEP_TIME":1602,"WHEELS_ON":1726,"TAXI_IN":7,"CRS_ARR_TIME":1648,"ARR_TIME":1733,"CANCELLED":0,"DISTANCE":1013}
{"FL_DATE":"2000-01-26","OP_CARRIER_FL_NUM":1601,"ORIGIN_CITY_NAME":"Nashville, TN","DEST":"DEN","DEST_CITY_NAME":"Denver, CO","CRS_DEP_TIME":735,"CRS_ARR_TIME":918,"CANCELLED":1,"DISTANCE":1013}
{"FL_DATE":"2000-01-26","OP_CARRIER_FL_NUM":589,"ORIGIN_CITY_NAME":"Nashville, TN","DEST":"ORD","DEST_CITY_NAME":"Chicago, IL","CRS_DEP_TIME":714,"DEP_TIME":711,"WHEELS_ON":835,"TAXI_IN":14,"CRS_ARR_TIME":845,"ARR_TIME":849,"CANCELLED":0,"DISTANCE":409}
{"FL_DATE":"2000-01-26","OP_CARRIER_FL_NUM":1101,"ORIGIN_CITY_NAME":"Nashville, TN","DEST":"ORD","DEST_CITY_NAME":"Chicago, IL","CRS_DEP_TIME":1710,"DEP_TIME":1708,"WHEELS_ON":1835,"TAXI_IN":8,"CRS_ARR_TIME":1841,"ARR_TIME":1843,"CANCELLED":0,"DISTANCE":409}
{"FL_DATE":"2000-01-26","OP_CARRIER_FL_NUM":1862,"ORIGIN_CITY_NAME":"Nashville, TN","DEST":"ORD","DEST_CITY_NAME":"Chicago, IL","CRS_DEP_TIME":942,"DEP_TIME":937,"WHEELS_ON":1102,"TAXI_IN":7,"CRS_ARR_TIME":1115,"ARR_TIME":1109,"CANCELLED":0,"DISTANCE":409}
{"FL_DATE":"2000-01-27","OP_CARRIER_FL_NUM":435,"ORIGIN_CITY_NAME":"Nashville, TN","DEST":"DEN","DEST_CITY_NAME":"Denver, CO","CRS_DEP_TIME":1510,"DEP_TIME":1520,"WHEELS_ON":1651,"TAXI_IN":5,"CRS_ARR_TIME":1648,"ARR_TIME":1656,"CANCELLED":0,"DISTANCE":1013}
{"FL_DATE":"2000-01-27","OP_CARRIER_FL_NUM":1601,"ORIGIN_CITY_NAME":"Nashville, TN","DEST":"DEN","DEST_CITY_NAME":"Denver, CO","CRS_DEP_TIME":735,"DEP_TIME":731,"WHEELS_ON":910,"TAXI_IN":4,"CRS_ARR_TIME":918,"ARR_TIME":914,"CANCELLED":0,"DISTANCE":1013}
{"FL_DATE":"2000-01-27","OP_CARRIER_FL_NUM":589,"ORIGIN_CITY_NAME":"Nashville, TN","DEST":"ORD","DEST_CITY_NAME":"Chicago, IL","CRS_DEP_TIME":714,"DEP_TIME":712,"WHEELS_ON":851,"TAXI_IN":8,"CRS_ARR_TIME":845,"ARR_TIME":859,"CANCELLED":0,"DISTANCE":409}
{"FL_DATE":"2000-01-27","OP_CARRIER_FL_NUM":1101,"ORIGIN_CITY_NAME":"Nashville, TN","DEST":"ORD","DEST_CITY_NAME":"Chicago, IL","CRS_DEP_TIME":1710,"DEP_TIME":1705,"WHEELS_ON":1844,"TAXI_IN":9,"CRS_ARR_TIME":1841,"ARR_TIME":1853,"CANCELLED":0,"DISTANCE":409}
{"FL_DATE":"2000-01-27","OP_CARRIER_FL_NUM":1862,"ORIGIN_CITY_NAME":"Nashville, TN","DEST":"ORD","DEST_CITY_NAME":"Chicago, IL","CRS_DEP_TIME":942,"DEP_TIME":946,"WHEELS_ON":1200,"TAXI_IN":10,"CRS_ARR_TIME":1115,"ARR_TIME":1210,"CANCELLED":0,"DISTANCE":409}
{"FL_DATE":"2000-01-28","OP_CARRIER_FL_NUM":435,"ORIGIN_CITY_NAME":"Nashville, TN","DEST":"DEN","DEST_CITY_NAME":"Denver, CO","CRS_DEP_TIME":1510,"DEP_TIME":1510,"WHEELS_ON":1645,"TAXI_IN":4,"CRS_ARR_TIME":1648,"ARR_TIME":1649,"CANCELLED":0,"DISTANCE":1013}
{"FL_DATE":"2000-01-28","OP_CARRIER_FL_NUM":1601,"ORIGIN_CITY_NAME":"Nashville, TN","DEST":"DEN","DEST_CITY_NAME":"Denver, CO","CRS_DEP_TIME":735,"DEP_TIME":732,"WHEELS_ON":858,"TAXI_IN":5,"CRS_ARR_TIME":918,"ARR_TIME":903,"CANCELLED":0,"DISTANCE":1013}
{"FL_DATE":"2000-01-28","OP_CARRIER_FL_NUM":589,"ORIGIN_CITY_NAME":"Nashville, TN","DEST":"ORD","DEST_CITY_NAME":"Chicago, IL","CRS_DEP_TIME":714,"DEP_TIME":708,"WHEELS_ON":825,"TAXI_IN":4,"CRS_ARR_TIME":845,"ARR_TIME":829,"CANCELLED":0,"DISTANCE":409}
{"FL_DATE":"2000-01-28","OP_CARRIER_FL_NUM":1101,"ORIGIN_CITY_NAME":"Nashville, TN","DEST":"ORD","DEST_CITY_NAME":"Chicago, IL","CRS_DEP_TIME":1710,"DEP_TIME":1704,"WHEELS_ON":1823,"TAXI_IN":7,"CRS_ARR_TIME":1841,"ARR_TIME":1830,"CANCELLED":0,"DISTANCE":409}
{"FL_DATE":"2000-01-28","OP_CARRIER_FL_NUM":1862,"ORIGIN_CITY_NAME":"Nashville, TN","DEST":"ORD","DEST_CITY_NAME":"Chicago, IL","CRS_DEP_TIME":942,"DEP_TIME":936,"WHEELS_ON":1103,"TAXI_IN":3,"CRS_ARR_TIME":1115,"ARR_TIME":1106,"CANCELLED":0,"DISTANCE":409}
{"FL_DATE":"2000-01-29","OP_CARRIER_FL_NUM":435,"ORIGIN_CITY_NAME":"Nashville, TN","DEST":"DEN","DEST_CITY_NAME":"Denver, CO","CRS_DEP_TIME":1510,"DEP_TIME":1513,"WHEELS_ON":1642,"TAXI_IN":4,"CRS_ARR_TIME":1648,"ARR_TIME":1646,"CANCELLED":0,"DISTANCE":1013}
{"FL_DATE":"2000-01-29","OP_CARRIER_FL_NUM":1601,"ORIGIN_CITY_NAME":"Nashville, TN","DEST":"DEN","DEST_CITY_NAME":"Denver, CO","CRS_DEP_TIME":735,"DEP_TIME":755,"WHEELS_ON":920,"TAXI_IN":5,"CRS_ARR_TIME":918,"ARR_TIME":925,"CANCELLED":0,"DISTANCE":1013}
{"FL_DATE":"2000-01-29","OP_CARRIER_FL_NUM":589,"ORIGIN_CITY_NAME":"Nashville, TN","DEST":"ORD","DEST_CITY_NAME":"Chicago, IL","CRS_DEP_TIME":714,"DEP_TIME":722,"WHEELS_ON":845,"TAXI_IN":8,"CRS_ARR_TIME":845,"ARR_TIME":853,"CANCELLED":0,"DISTANCE":409}
{"FL_DATE":"2000-01-29","OP_CARRIER_FL_NUM":1101,"ORIGIN_CITY_NAME":"Nashville, TN","DEST":"ORD","DEST_CITY_NAME":"Chicago, IL","CRS_DEP_TIME":1710,"DEP_TIME":1702,"WHEELS_ON":1830,"TAXI_IN":7,"CRS_ARR_TIME":1841,"ARR_TIME":1837,"CANCELLED":0,"DISTANCE":409}
{"FL_DATE":"2000-01-29","OP_CARRIER_FL_NUM":1862,"ORIGIN_CITY_NAME":"Nashville, TN","DEST":"ORD","DEST_CITY_NAME":"Chicago, IL","CRS_DEP_TIME":942,"DEP_TIME":936,"WHEELS_ON":1054,"TAXI_IN":10,"CRS_ARR_TIME":1115,"ARR_TIME":1104,"CANCELLED":0,"DISTANCE":409}
{"FL_DATE":"2000-01-30","OP_CARRIER_FL_NUM":435,"ORIGIN_CITY_NAME":"Nashville, TN","DEST":"DEN","DEST_CITY_NAME":"Denver, CO","CRS_DEP_TIME":1510,"DEP_TIME":1509,"WHEELS_ON":1640,"TAXI_IN":5,"CRS_ARR_TIME":1648,"ARR_TIME":1645,"CANCELLED":0,"DISTANCE":1013}
{"FL_DATE":"2000-01-30","OP_CARRIER_FL_NUM":1601,"ORIGIN_CITY_NAME":"Nashville, TN","DEST":"DEN","DEST_CITY_NAME":"Denver, CO","CRS_DEP_TIME":735,"DEP_TIME":734,"WHEELS_ON":914,"TAXI_IN":5,"CRS_ARR_TIME":918,"ARR_TIME":919,"CANCELLED":0,"DISTANCE":1013}
{"FL_DATE":"2000-01-30","OP_CARRIER_FL_NUM":1101,"ORIGIN_CITY_NAME":"Nashville, TN","DEST":"ORD","DEST_CITY_NAME":"Chicago, IL","CRS_DEP_TIME":1710,"DEP_TIME":1720,"WHEELS_ON":1851,"TAXI_IN":5,"CRS_ARR_TIME":1841,"ARR_TIME":1856,"CANCELLED":0,"DISTANCE":409}
{"FL_DATE":"2000-01-30","OP_CARRIER_FL_NUM":1862,"ORIGIN_CITY_NAME":"Nashville, TN","DEST":"ORD","DEST_CITY_NAME":"Chicago, IL","CRS_DEP_TIME":942,"DEP_TIME":935,"WHEELS_ON":1058,"TAXI_IN":7,"CRS_ARR_TIME":1115,"ARR_TIME":1105,"CANCELLED":0,"DISTANCE":409}
{"FL_DATE":"2000-01-31","OP_CARRIER_FL_NUM":435,"ORIGIN_CITY_NAME":"Nashville, TN","DEST":"DEN","DEST_CITY_NAME":"Denver, CO","CRS_DEP_TIME":1510,"CRS_ARR_TIME":1648,"CANCELLED":1,"DISTANCE":1013}
{"FL_DATE":"2000-01-31","OP_CARRIER_FL_NUM":1601,"ORIGIN_CITY_NAME":"Nashville, TN","DEST":"DEN","DEST_CITY_NAME":"Denver, CO","CRS_DEP_TIME":735,"DEP_TIME":732,"WHEELS_ON":849,"TAXI_IN":5,"CRS_ARR_TIME":918,"ARR_TIME":854,"CANCELLED":0,"DISTANCE":1013}
{"FL_DATE":"2000-01-31","OP_CARRIER_FL_NUM":589,"ORIGIN_CITY_NAME":"Nashville, TN","DEST":"ORD","DEST_CITY_NAME":"Chicago, IL","CRS_DEP_TIME":714,"DEP_TIME":711,"WHEELS_ON":839,"TAXI_IN":4,"CRS_ARR_TIME":845,"ARR_TIME":843,"CANCELLED":0,"DISTANCE":409}
{"FL_DATE":"2000-01-31","OP_CARRIER_FL_NUM":1101,"ORIGIN_CITY_NAME":"Nashville, TN","DEST":"ORD","DEST_CITY_NAME":"Chicago, IL","CRS_DEP_TIME":1710,"DEP_TIME":1856,"WHEELS_ON":2025,"TAXI_IN":4,"CRS_ARR_TIME":1841,"ARR_TIME":2029,"CANCELLED":0,"DISTANCE":409}
{"FL_DATE":"2000-01-31","OP_CARRIER_FL_NUM":1862,"ORIGIN_CITY_NAME":"Nashville, TN","DEST":"ORD","DEST_CITY_NAME":"Chicago, IL","CRS_DEP_TIME":942,"DEP_TIME":953,"WHEELS_ON":1118,"TAXI_IN":8,"CRS_ARR_TIME":1115,"ARR_TIME":1126,"CANCELLED":0,"DISTANCE":409}
