{"FL_DATE":"2000-01-23","OP_CARRIER_FL_NUM":690,"ORIGIN_CITY_NAME":"Minneapolis, MN","DEST":"EWR","DEST_CITY_NAME":"Newark, NJ","CRS_DEP_TIME":1255,"DEP_TIME":1319,"WHEELS_ON":1707,"TAXI_IN":8,"CRS_ARR_TIME":1635,"ARR_TIME":1715,"CANCELLED":0,"DISTANCE":1008}
{"FL_DATE":"2000-01-23","OP_CARRIER_FL_NUM":694,"ORIGIN_CITY_NAME":"Minneapolis, MN","DEST":"EWR","DEST_CITY_NAME":"Newark, NJ","CRS_DEP_TIME":1830,"DEP_TIME":1833,"WHEELS_ON":2202,"TAXI_IN":5,"CRS_ARR_TIME":2211,"ARR_TIME":2207,"CANCELLED":0,"DISTANCE":1008}
{"FL_DATE":"2000-01-23","OP_CARRIER_FL_NUM":698,"ORIGIN_CITY_NAME":"Minneapolis, MN","DEST":"EWR","DEST_CITY_NAME":"Newark, NJ","CRS_DEP_TIME":920,"DEP_TIME":914,"WHEELS_ON":1233,"TAXI_IN":4,"CRS_ARR_TIME":1253,"ARR_TIME":1237,"CANCELLED":0,"DISTANCE":1008}
{"FL_DATE":"2000-01-24","OP_CARRIER_FL_NUM":235,"ORIGIN_CITY_NAME":"Minneapolis, MN","DEST":"IAH","DEST_CITY_NAME":"Houston, TX","CRS_DEP_TIME":1809,"DEP_TIME":1813,"WHEELS_ON":2050,"TAXI_IN":10,"CRS_ARR_TIME":2105,"ARR_TIME":2100,"CANCELLED":0,"DISTANCE":1034}
{"FL_DATE":"2000-01-24","OP_CARRIER_FL_NUM":1227,"ORIGIN_CITY_NAME":"Minneapolis, MN","DEST":"IAH","DEST_CITY_NAME":"Houston, TX","CRS_DEP_TIME":1335,"DEP_TIME":1329,"WHEELS_ON":1558,"TAXI_IN":9,"CRS_ARR_TIME":1639,"ARR_TIME":1607,"CANCELLED":0,"DISTANCE":1034}
{"FL_DATE":"2000-01-24","OP_CARRIER_FL_NUM":1559,"ORIGIN_CITY_NAME":"Minneapolis, MN","DEST":"IAH","DEST_CITY_NAME":"Houston, TX","CRS_DEP_TIME":600,"DEP_TIME":600,"WHEELS_ON":835,"TAXI_IN":5,"CRS_ARR_TIME":850,"ARR_TIME":840,"CANCELLED":0,"DISTANCE":1034}
{"FL_DATE":"2000-01-24","OP_CARRIER_FL_NUM":323,"ORIGIN_CITY_NAME":"Minneapolis, MN","DEST":"EWR","DEST_CITY_NAME":"Newark, NJ","CRS_DEP_TIME":1255,"DEP_TIME":1252,"WHEELS_ON":1622,"TAXI_IN":12,"CRS_ARR_TIME":1635,"ARR_TIME":1634,"CANCELLED":0,"DISTANCE":1008}
{"FL_DATE":"2000-01-24","OP_CARRIER_FL_NUM":694,"ORIGIN_CITY_NAME":"Minneapolis, MN","DEST":"EWR","DEST_CITY_NAME":"Newark, NJ","CRS_DEP_TIME":1830,"DEP_TIME":1835,"WHEELS_ON":2203,"TAXI_IN":7,"CRS_ARR_TIME":2211,"ARR_TIME":2210,"CANCELLED":0,"DISTANCE":1008}
{"FL_DATE":"2000-01-24","OP_CARRIER_FL_NUM":696,"ORIGIN_CITY_NAME":"Minneapolis, MN","DEST":"EWR","DEST_CITY_NAME":"Newark, NJ","CRS_DEP_TIME":715,"DEP_TIME":709,"WHEELS_ON":1041,"TAXI_IN":5,"CRS_ARR_TIME":1050,"ARR_TIME":1046,"CANCELLED":0,"DISTANCE":1008}
{"FL_DATE":"2000-01-24","OP_CARRIER_FL_NUM":698,"ORIGIN_CITY_NAME":"Minneapolis, MN","DEST":"EWR","DEST_CITY_NAME":"Newark, NJ","CRS_DEP_TIME":920,"DEP_TIME":1054,"WHEELS_ON":1418,"TAXI_IN":6,"CRS_ARR_TIME":1253,"ARR_TIME":1424,"CANCELLED":0,"DISTANCE":1008}
{"FL_DATE":"2000-01-25","OP_CARRIER_FL_NUM":323,"ORIGIN_CITY_NAME":"Minneapolis, MN","DEST":"EWR","DEST_CITY_NAME":"Newark, NJ","CRS_DEP_TIME":1255,"CRS_ARR_TIME":1635,"CANCELLED":1,"DISTANCE":1008}
{"FL_DATE":"2000-01-25","OP_CARRIER_FL_NUM":694,"ORIGIN_CITY_NAME":"Minneapolis, MN","DEST":"EWR","DEST_CITY_NAME":"Newark, NJ","CRS_DEP_TIME":1830,"CRS_ARR_TIME":2211,"CANCELLED":1,"DISTANCE":1008}
{"FL_DATE":"2000-01-25","OP_CARRIER_FL_NUM":696,"ORIGIN_CITY_NAME":"Minneapolis, MN","DEST":"EWR","DEST_CITY_NAME":"Newark, NJ","CRS_DEP_TIME":715,"CRS_ARR_TIME":1050,"CANCELLED":1,"DISTANCE":1008}
{"FL_DATE":"2000-01-25","OP_CARRIER_FL_NUM":698,"ORIGIN_CITY_NAME":"Minneapolis, MN","DEST":"EWR","DEST_CITY_NAME":"Newark, NJ","CRS_DEP_TIME":920,"CRS_ARR_TIME":1253,"CANCELLED":1,"DISTANCE":1008}
{"FL_DATE":"2000-01-25","OP_CARRIER_FL_NUM":235,"ORIGIN_CITY_NAME":"Minneapolis, MN","DEST":"IAH","DEST_CITY_NAME":"Houston, TX","CRS_DEP_TIME":1809,"DEP_TIME":1807,"WHEELS_ON":2025,"TAXI_IN":10,"CRS_ARR_TIME":2105,"ARR_TIME":2035,"CANCELLED":0,"DISTANCE":1034}
{"FL_DATE":"2000-01-25","OP_CARRIER_FL_NUM":1227,"ORIGIN_CITY_NAME":"Minneapolis, MN","DEST":"IAH","DEST_CITY_NAME":"Houston, TX","CRS_DEP_TIME":1335,"DEP_TIME":1333,"WHEELS_ON":1556,"TAXI_IN":5,"CRS_ARR_TIME":1639,"ARR_TIME":1601,"CANCELLED":0,"DISTANCE":1034}
{"FL_DATE":"2000-01-25","OP_CARRIER_FL_NUM":1559,"ORIGIN_CITY_NAME":"Minneapolis, MN","DEST":"IAH","DEST_CITY_NAME":"Houston, TX","CRS_DEP_TIME":600,"DEP_TIME":557,"WHEELS_ON":821,"TAXI_IN":5,"CRS_ARR_TIME":850,"ARR_TIME":826,"CANCELLED":0,"DISTANCE":1034}
{"FL_DATE":"2000-01-26","OP_CARRIER_FL_NUM":235,"ORIGIN_CITY_NAME":"Minneapolis, MN","DEST":"IAH","DEST_CITY_NAME":"Houston, TX","CRS_DEP_TIME":1809,"DEP_TIME":1804,"WHEELS_ON":2042,"TAXI_IN":13,"CRS_ARR_TIME":2105,"ARR_TIME":2055,"CANCELLED":0,"DISTANCE":1034}
{"FL_DATE":"2000-01-26","OP_CARRIER_FL_NUM":1227,"ORIGIN_CITY_NAME":"Minneapolis, MN","DEST":"IAH","DEST_CITY_NAME":"Houston, TX","CRS_DEP_TIME":1335,"DEP_TIME":1522,"WHEELS_ON":1800,"TAXI_IN":9,"CRS_ARR_TIME":1639,"ARR_TIME":1809,"CANCELLED":0,"DISTANCE":1034}
{"FL_DATE":"2000-01-26","OP_CARRIER_FL_NUM":1559,"ORIGIN_CITY_NAME":"Minneapolis, MN","DEST":"IAH","DEST_CITY_NAME":"Houston, TX","CRS_DEP_TIME":600,"DEP_TIME":600,"WHEELS_ON":830,"TAXI_IN":8,"CRS_ARR_TIME":850,"ARR_TIME":838,"CANCELLED":0,"DISTANCE":1034}
{"FL_DATE":"2000-01-26","OP_CARRIER_FL_NUM":323,"ORIGIN_CITY_NAME":"Minneapolis, MN","DEST":"EWR","DEST_CITY_NAME":"Newark, NJ","CRS_DEP_TIME":1255,"DEP_TIME":1250,"WHEELS_ON":1635,"TAXI_IN":9,"CRS_ARR_TIME":1635,"ARR_TIME":1644,"CANCELLED":0,"DISTANCE":1008}
{"FL_DATE":"2000-01-26","OP_CARRIER_FL_NUM":694,"ORIGIN_CITY_NAME":"Minneapolis, MN","DEST":"EWR","DEST_CITY_NAME":"Newark, NJ","CRS_DEP_TIME":1830,"DEP_TIME":1827,"WHEELS_ON":2139,"TAXI_IN":5,"CRS_ARR_TIME":2211,"ARR_TIME":2144,"CANCELLED":0,"DISTANCE":1008}
{"FL_DATE":"2000-01-26","OP_CARRIER_FL_NUM":696,"ORIGIN_CITY_NAME":"Minneapolis, MN","DEST":"EWR","DEST_CITY_NAME":"Newark, NJ","CRS_DEP_TIME":715,"DEP_TIME":713,"WHEELS_ON":1054,"TAXI_IN":7,"CRS_ARR_TIME":1050,"ARR_TIME":1101,"CANCELLED":0,"DISTANCE":1008}
{"FL_DATE":"2000-01-26","OP_CARRIER_FL_NUM":698,"ORIGIN_CITY_NAME":"Minneapolis, MN","DEST":"EWR","DEST_CITY_NAME":"Newark, NJ","CRS_DEP_TIME":920,"DEP_TIME":921,"WHEELS_ON":1250,"TAXI_IN":8,"CRS_ARR_TIME":1253,"ARR_TIME":1258,"CANCELLED":0,"DISTANCE":1008}
{"FL_DATE":"2000-01-27","OP_CARRIER_FL_NUM":323,"ORIGIN_CITY_NAME":"Minneapolis, MN","DEST":"EWR","DEST_CITY_NAME":"Newark, NJ","CRS_DEP_TIME":1255,"DEP_TIME":1255,"WHEELS_ON":1618,"TAXI_IN":10,"CRS_ARR_TIME":1635,"ARR_TIME":1628,"CANCELLED":0,"DISTANCE":1008}
{"FL_DATE":"2000-01-27","OP_CARRIER_FL_NUM":694,"ORIGIN_CITY_NAME":"Minneapolis, MN","DEST":"EWR","DEST_CITY_NAME":"Newark, NJ","CRS_DEP_TIME":1830,"DEP_TIME":1833,"WHEELS_ON":2153,"TAXI_IN":8,"CRS_ARR_TIME":2211,"ARR_TIME":2201,"CANCELLED":0,"DISTANCE":1008}
{"FL_DATE":"2000-01-27","OP_CARRIER_FL_NUM":696,"ORIGIN_CITY_NAME":"Minneapolis, MN","DEST":"EWR","DEST_CITY_NAME":"Newark, NJ","CRS_DEP_TIME":715,"DEP_TIME":708,"WHEELS_ON":1037,"TAXI_IN":8,"CRS_ARR_TIME":1050,"ARR_TIME":1045,"CANCELLED":0,"DISTANCE":1008}
{"FL_DATE":"2000-01-27","OP_CARRIER_FL_NUM":698,"ORIGIN_CITY_NAME":"Minneapolis, MN","DEST":"EWR","DEST_CITY_NAME":"Newark, NJ","CRS_DEP_TIME":920,"DEP_TIME":916,"WHEELS_ON":1232,"TAXI_IN":10,"CRS_ARR_TIME":1253,"ARR_TIME":1242,"CANCELLED":0,"DISTANCE":1008}
{"FL_DATE":"2000-01-27","OP_CARRIER_FL_NUM":235,"ORIGIN_CITY_NAME":"Minneapolis, MN","DEST":"IAH","DEST_CITY_NAME":"Houston, TX","CRS_DEP_TIME":1809,"DEP_TIME":1835,"WHEELS_ON":2116,"TAXI_IN":6,"CRS_ARR_TIME":2105,"ARR_TIME":2122,"CANCELLED":0,"DISTANCE":1034}
{"FL_DATE":"2000-01-27","OP_CARRIER_FL_NUM":1227,"ORIGIN_CITY_NAME":"Minneapolis, MN","DEST":"IAH","DEST_CITY_NAME":"Houston, TX","CRS_DEP_TIME":1335,"DEP_TIME":1341,"WHEELS_ON":1630,"TAXI_IN":7,"CRS_ARR_TIME":1639,"ARR_TIME":1637,"CANCELLED":0,"DISTANCE":1034}
{"FL_DATE":"2000-01-27","OP_CARRIER_FL_NUM":1559,"ORIGIN_CITY_NAME":"Minneapolis, MN","DEST":"IAH","DEST_CITY_NAME":"Houston, TX","CRS_DEP_TIME":600,"DEP_TIME":559,"WHEELS_ON":915,"TAXI_IN":12,"CRS_ARR_TIME":850,"ARR_TIME":927,"CANCELLED":0,"DISTANCE":1034}
{"FL_DATE":"2000-01-28","OP_CARRIER_FL_NUM":235,"ORIGIN_CITY_NAME":"Minneapolis, MN","DEST":"IAH","DEST_CITY_NAME":"Houston, TX","CRS_DEP_TIME":1809,"DEP_TIME":1809,"WHEELS_ON":2045,"TAXI_IN":5,"CRS_ARR_TIME":2105,"ARR_TIME":2050,"CANCELLED":0,"DISTANCE":1034}
{"FL_DATE":"2000-01-28","OP_CARRIER_FL_NUM":1227,"ORIGIN_CITY_NAME":"Minneapolis, MN","DEST":"IAH","DEST_CITY_NAME":"Houston, TX","CRS_DEP_TIME":1335,"DEP_TIME":1330,"WHEELS_ON":1616,"TAXI_IN":5,"CRS_ARR_TIME":1639,"ARR_TIME":1621,"CANCELLED":0,"DISTANCE":1034}
{"FL_DATE":"2000-01-28","OP_CARRIER_FL_NUM":1559,"ORIGIN_CITY_NAME":"Minneapolis, MN","DEST":"IAH","DEST_CITY_NAME":"Houston, TX","CRS_DEP_TIME":600,"DEP_TIME":557,"WHEELS_ON":847,"TAXI_IN":5,"CRS_ARR_TIME":850,"ARR_TIME":852,"CANCELLED":0,"DISTANCE":1034}
{"FL_DATE":"2000-01-28","OP_CARRIER_FL_NUM":323,"ORIGIN_CITY_NAME":"Minneapolis, MN","DEST":"EWR","DEST_CITY_NAME":"Newark, NJ","CRS_DEP_TIME":1255,"DEP_TIME":1401,"WHEELS_ON":1740,"TAXI_IN":9,"CRS_ARR_TIME":1635,"ARR_TIME":1749,"CANCELLED":0,"DISTANCE":1008}
{"FL_DATE":"2000-01-28","OP_CARRIER_FL_NUM":694,"ORIGIN_CITY_NAME":"Minneapolis, MN","DEST":"EWR","DEST_CITY_NAME":"Newark, NJ","CRS_DEP_TIME":1830,"CRS_ARR_TIME":2211,"CANCELLED":1,"DISTANCE":1008}
{"FL_DATE":"2000-01-28","OP_CARRIER_FL_NUM":696,"ORIGIN_CITY_NAME":"Minneapolis, MN","DEST":"EWR","DEST_CITY_NAME":"Newark, NJ","CRS_DEP_TIME":715,"DEP_TIME":710,"WHEELS_ON":1120,"TAXI_IN":5,"CRS_ARR_TIME":1050,"ARR_TIME":1125,"CANCELLED":0,"DISTANCE":1008}
{"FL_DATE":"2000-01-28","OP_CARRIER_FL_NUM":698,"ORIGIN_CITY_NAME":"Minneapolis, MN","DEST":"EWR","DEST_CITY_NAME":"Newark, NJ","CRS_DEP_TIME":920,"DEP_TIME":914,"WHEELS_ON":1236,"TAXI_IN":6,"CRS_ARR_TIME":1253,"ARR_TIME":1242,"CANCELLED":0,"DISTANCE":1008}
{"FL_DATE":"2000-01-29","OP_CARRIER_FL_NUM":323,"ORIGIN_CITY_NAME":"Minneapolis, MN","DEST":"EWR","DEST_CITY_NAME":"Newark, NJ","CRS_DEP_TIME":1255,"DEP_TIME":1250,"WHEELS_ON":1622,"TAXI_IN":6,"CRS_ARR_TIME":1635,"ARR_TIME":1628,"CANCELLED":0,"DISTANCE":1008}
{"FL_DATE":"2000-01-29","OP_CARRIER_FL_NUM":698,"ORIGIN_CITY_NAME":"Minneapolis, MN","DEST":"EWR","DEST_CITY_NAME":"Newark, NJ","CRS_DEP_TIME":920,"DEP_TIME":912,"WHEELS_ON":1234,"TAXI_IN":4,"CRS_ARR_TIME":1253,"ARR_TIME":1238,"CANCELLED":0,"DISTANCE":1008}
{"FL_DATE":"2000-01-29","OP_CARRIER_FL_NUM":1227,"ORIGIN_CITY_NAME":"Minneapolis, MN","DEST":"IAH","DEST_CITY_NAME":"Houston, TX","CRS_DEP_TIME":1335,"DEP_TIME":1331,"WHEELS_ON":1628,"TAXI_IN":5,"CRS_ARR_TIME":1639,"ARR_TIME":1633,"CANCELLED":0,"DISTANCE":1034}
{"FL_DATE":"2000-01-29","OP_CARRIER_FL_NUM":1559,"ORIGIN_CITY_NAME":"Minneapolis, MN","DEST":"IAH","DEST_CITY_NAME":"Houston, TX","CRS_DEP_TIME":600,"DEP_TIME":605,"WHEELS_ON":840,"TAXI_IN":8,"CRS_ARR_TIME":850,"ARR_TIME":848,"CANCELLED":0,"DISTANCE":1034}
{"FL_DATE":"2000-01-30","OP_CARRIER_FL_NUM":227,"ORIGIN_CITY_NAME":"Minneapolis, MN","DEST":"IAH","DEST_CITY_NAME":"Houston, TX","CRS_DEP_TIME":710,"DEP_TIME":705,"WHEELS_ON":946,"TAXI_IN":6,"CRS_ARR_TIME":1010,"ARR_TIME":952,"CANCELLED":0,"DISTANCE":1034}
{"FL_DATE":"2000-01-30","OP_CARRIER_FL_NUM":235,"ORIGIN_CITY_NAME":"Minneapolis, MN","DEST":"IAH","DEST_CITY_NAME":"Houston, TX","CRS_DEP_TIME":1809,"DEP_TIME":1804,"WHEELS_ON":2029,"TAXI_IN":9,"CRS_ARR_TIME":2105,"ARR_TIME":2038,"CANCELLED":0,"DISTANCE":1034}
{"FL_DATE":"2000-01-30","OP_CARRIER_FL_NUM":1227,"ORIGIN_CITY_NAME":"Minneapolis, MN","DEST":"IAH","DEST_CITY_NAME":"Houston, TX","CRS_DEP_TIME":1335,"DEP_TIME":1329,"WHEELS_ON":1608,"TAXI_IN":3,"CRS_ARR_TIME":1639,"ARR_TIME":1611,"CANCELLED":0,"DISTANCE":1034}
{"FL_DATE":"2000-01-30","OP_CARRIER_FL_NUM":690,"ORIGIN_CITY_NAME":"Minneapolis, MN","DEST":"EWR","DEST_CITY_NAME":"Newark, NJ","CRS_DEP_TIME":1255,"DEP_TIME":1252,"WHEELS_ON":1620,"TAXI_IN":6,"CRS_ARR_TIME":1635,"ARR_TIME":1626,"CANCELLED":0,"DISTANCE":1008}
{"FL_DATE":"2000-01-30","OP_CARRIER_FL_NUM":694,"ORIGIN_CITY_NAME":"Minneapolis, MN","DEST":"EWR","DEST_CITY_NAME":"Newark, NJ","CRS_DEP_TIME":1830,"DEP_TIME":1828,"WHEELS_ON":2251,"TAXI_IN":11,"CRS_ARR_TIME":2211,"ARR_TIME":2302,"CANCELLED":0,"DISTANCE":1008}
{"FL_DATE":"2000-01-30","OP_CARRIER_FL_NUM":698,"ORIGIN_CITY_NAME":"Minneapolis, MN","DEST":"EWR","DEST_CITY_NAME":"Newark, NJ","CRS_DEP_TIME":920,"DEP_TIME":921,"WHEELS_ON":1252,"TAXI_IN":6,"CRS_ARR_TIME":1253,"ARR_TIME":1258,"CANCELLED":0,"DISTANCE":1008}
{"FL_DATE":"2000-01-31","OP_CARRIER_FL_NUM":323,"ORIGIN_CITY_NAME":"Minneapolis, MN","DEST":"EWR","DEST_CITY_NAME":"Newark, NJ","CRS_DEP_TIME":1255,"DEP_TIME":1252,"WHEELS_ON":1621,"TAXI_IN":6,"CRS_ARR_TIME":1635,"ARR_TIME":1627,"CANCELLED":0,"DISTANCE":1008}
{"FL_DATE":"2000-01-31","OP_CARRIER_FL_NUM":694,"ORIGIN_CITY_NAME":"Minneapolis, MN","DEST":"EWR","DEST_CITY_NAME":"Newark, NJ","CRS_DEP_TIME":1830,"DEP_TIME":1829,"WHEELS_ON":2149,"TAXI_IN":21,"CRS_ARR_TIME":2211,"ARR_TIME":2210,"CANCELLED":0,"DISTANCE":1008}
{"FL_DATE":"2000-01-31","OP_CARRIER_FL_NUM":696,"ORIGIN_CITY_NAME":"Minneapolis, MN","DEST":"EWR","DEST_CITY_NAME":"Newark, NJ","CRS_DEP_TIME":715,"DEP_TIME":715,"WHEELS_ON":1045,"TAXI_IN":9,"CRS_ARR_TIME":1050,"ARR_TIME":1054,"CANCELLED":0,"DISTANCE":1008}
{"FL_DATE":"2000-01-31","OP_CARRIER_FL_NUM":698,"ORIGIN_CITY_NAME":"Minneapolis, MN","DEST":"EWR","DEST_CITY_NAME":"Newark, NJ","CRS_DEP_TIME":920,"CRS_ARR_TIME":1253,"CANCELLED":1,"DISTANCE":1008}
{"FL_DATE":"2000-01-31","OP_CARRIER_FL_NUM":235,"ORIGIN_CITY_NAME":"Minneapolis, MN","DEST":"IAH","DEST_CITY_NAME":"Houston, TX","CRS_DEP_TIME":1809,"DEP_TIME":1803,"WHEELS_ON":2043,"TAXI_IN":10,"CRS_ARR_TIME":2105,"ARR_TIME":2053,"CANCELLED":0,"DISTANCE":1034}
{"FL_DATE":"2000-01-31","OP_CARRIER_FL_NUM":1227,"ORIGIN_CITY_NAME":"Minneapolis, MN","DEST":"IAH","DEST_CITY_NAME":"Houston, TX","CRS_DEP_TIME":1335,"DEP_TIME":1330,"WHEELS_ON":1613,"TAXI_IN":5,"CRS_ARR_TIME":1639,"ARR_TIME":1618,"CANCELLED":0,"DISTANCE":1034}
{"FL_DATE":"2000-01-31","OP_CARRIER_FL_NUM":1559,"ORIGIN_CITY_NAME":"Minneapolis, MN","DEST":"IAH","DEST_CITY_NAME":"Houston, TX","CRS_DEP_TIME":600,"DEP_TIME":603,"WHEELS_ON":847,"TAXI_IN":4,"CRS_ARR_TIME":850,"ARR_TIME":851,"CANCELLED":0,"DISTANCE":1034}
